pydia/__init__.py
pydia/pydia.pyd
pydia3-0.1.5.dist-info/METADATA
pydia3-0.1.5.dist-info/WHEEL
pydia3-0.1.5.dist-info/top_level.txt
pydia3-0.1.5.dist-info/RECORD
