Metadata-Version: 2.1
Name: pydia3
Version: 0.1.5
Summary: Python interface for Microsoft's Debug Interface Access (DIA) SDK.
Home-page: https://github.com/Michael-K-Stein/pydia
Author: Michael K. Steinberg
Author-email: m.kuper.steinberg@gmail.com
License: MIT
Classifier: Programming Language :: Python :: 3
Classifier: Operating System :: Microsoft :: Windows
Requires-Python: >=3.12
